keybow/__init__.py
keybow-0.0.3.dist-info/LICENSE.txt
keybow-0.0.3.dist-info/METADATA
keybow-0.0.3.dist-info/WHEEL
keybow-0.0.3.dist-info/top_level.txt
keybow-0.0.3.dist-info/RECORD
