Metadata-Version: 2.1
Name: keybow
Version: 0.0.3
Summary: Keybow 3 and 12 key, backlit mechanical keyboard add-ons for the Raspberry Pi
Home-page: https://www.pimoroni.com
Author: Philip Howard
Author-email: phil@pimoroni.com
License: MIT
Project-URL: GitHub, https://www.github.com/pimoroni/keybow-python
Keywords: Raspberry Pi
Platform: UNKNOWN
Classifier: Development Status :: 4 - Beta
Classifier: Operating System :: POSIX :: Linux
Classifier: License :: OSI Approved :: MIT License
Classifier: Intended Audience :: Developers
Classifier: Programming Language :: Python :: 2.6
Classifier: Programming Language :: Python :: 2.7
Classifier: Programming Language :: Python :: 3
Classifier: Topic :: Software Development
Classifier: Topic :: Software Development :: Libraries
Classifier: Topic :: System :: Hardware
Requires-Dist: setuptools (>=30.4.0)
